arch_dp/data_preprocessing.py
data_preprocessing_arch-0.0.1.dist-info/METADATA
data_preprocessing_arch-0.0.1.dist-info/WHEEL
data_preprocessing_arch-0.0.1.dist-info/top_level.txt
data_preprocessing_arch-0.0.1.dist-info/RECORD
